odoo/addons/sm_contributions/__init__.py
odoo/addons/sm_contributions/__manifest__.py
odoo/addons/sm_contributions/data/sm_account_journal.xml
odoo/addons/sm_contributions/email_tmpl/contributions_contract.xml
odoo/addons/sm_contributions/email_tmpl/contributions_contract_2.xml
odoo/addons/sm_contributions/email_tmpl/contributions_contract_3.xml
odoo/addons/sm_contributions/email_tmpl/contributions_year_line.xml
odoo/addons/sm_contributions/models/__init__.py
odoo/addons/sm_contributions/models/models_sm_company.py
odoo/addons/sm_contributions/models/models_sm_contribution.py
odoo/addons/sm_contributions/models/models_sm_contribution_interest.py
odoo/addons/sm_contributions/models/models_sm_contribution_line.py
odoo/addons/sm_contributions/models/models_sm_contribution_type.py
odoo/addons/sm_contributions/models/models_sm_res_config_settings.py
odoo/addons/sm_contributions/report/sm_contributions_contract.xml
odoo/addons/sm_contributions/report/sm_contributions_contract_2.xml
odoo/addons/sm_contributions/report/sm_contributions_contract_3.xml
odoo/addons/sm_contributions/report/sm_contributions_report.xml
odoo/addons/sm_contributions/report/sm_contributions_report_line.xml
odoo/addons/sm_contributions/security/ir.model.access.csv
odoo/addons/sm_contributions/static/firm.png
odoo/addons/sm_contributions/views/views.xml
odoo/addons/sm_contributions/views/views_contribution.xml
odoo/addons/sm_contributions/views/views_contribution_interest.xml
odoo/addons/sm_contributions/views/views_contribution_line.xml
odoo/addons/sm_contributions/views/views_contribution_type.xml
odoo/addons/sm_contributions/views/views_res_config_settings.xml
odoo/addons/sm_contributions/wizards/__init__.py
odoo/addons/sm_contributions/wizards/wizards_sm_date_picker.py
odoo/addons/sm_contributions/wizards/wizards_sm_date_picker.xml
odoo/addons/sm_contributions/wizards/wizards_sm_select_year_line.py
odoo/addons/sm_contributions/wizards/wizards_sm_select_year_line.xml
odoo12_addon_sm_contributions-12.0.0.0.7.dist-info/METADATA
odoo12_addon_sm_contributions-12.0.0.0.7.dist-info/WHEEL
odoo12_addon_sm_contributions-12.0.0.0.7.dist-info/top_level.txt
odoo12_addon_sm_contributions-12.0.0.0.7.dist-info/RECORD
